README.rst
setup.py
tfgraph/__init__.py
tfgraph.egg-info/PKG-INFO
tfgraph.egg-info/SOURCES.txt
tfgraph.egg-info/dependency_links.txt
tfgraph.egg-info/not-zip-safe
tfgraph.egg-info/requires.txt
tfgraph.egg-info/top_level.txt
tfgraph/algorithms/__init__.py
tfgraph/algorithms/pagerank/__init__.py
tfgraph/algorithms/pagerank/algebraic_pagerank.py
tfgraph/algorithms/pagerank/iterative_pagerank.py
tfgraph/algorithms/pagerank/pagerank.py
tfgraph/algorithms/pagerank/transition/__init__.py
tfgraph/algorithms/pagerank/transition/transition.py
tfgraph/algorithms/pagerank/transition/transition_matrix.py
tfgraph/algorithms/pagerank/transition/transition_reset_matrix.py
tfgraph/graph/__init__.py
tfgraph/graph/graph.py
tfgraph/graph/graph_constructor.py
tfgraph/graph/graph_sparsifier.py
tfgraph/utils/__init__.py
tfgraph/utils/datasets.py
tfgraph/utils/tensorflow_object.py
tfgraph/utils/utils.py
tfgraph/utils/callbacks/__init__.py
tfgraph/utils/callbacks/update_edge_listener.py
tfgraph/utils/callbacks/update_edge_notifier.py
tfgraph/utils/math/__init__.py
tfgraph/utils/math/convergence_criterion.py
tfgraph/utils/math/vector_norm.py