Metadata-Version: 1.2
Name: tfgraph
Version: 0.2
Summary: Python's Tensorflow Graph Library
Home-page: http://tfgraph.readthedocs.io/en/latest/
Author: garciparedes
Author-email: sergio@garciparedes.me
License: UNKNOWN
Download-URL: https://github.com/tfgraph/tfgraph
Keywords: tfg,bigdata,tensorflow,graph theory,pagerank,university of valladolid
Platform: UNKNOWN
Classifier: Development Status :: 2 - Pre-Alpha
Classifier: Intended Audience :: Education
Classifier: Intended Audience :: Science/Research
Classifier: Operating System :: OS Independent
Classifier: Programming Language :: Python
Classifier: Programming Language :: Python :: 3
Classifier: Programming Language :: Python :: 3.5
Classifier: Programming Language :: Python :: Implementation :: CPython
Classifier: Topic :: Scientific/Engineering
Classifier: Topic :: Scientific/Engineering :: Mathematics
Requires-Python: >=3.5
